dator/__init__.py
dator/datastorages/__init__.py
dator/datastorages/bigquery.py
dator/datastorages/carto.py
dator/datastorages/csv.py
dator/datastorages/postgresql.py
dator/schemas.py
dator/transformers/__init__.py
dator/transformers/bigquery.py
dator/transformers/pandas.py
dator/transformers/postgresql.py
dator/utils.py
geolibs_dator-0.0.7.dist-info/LICENSE
geolibs_dator-0.0.7.dist-info/WHEEL
geolibs_dator-0.0.7.dist-info/METADATA
geolibs_dator-0.0.7.dist-info/RECORD
