Metadata-Version: 2.1
Name: geolibs-dator
Version: 0.0.7
Summary: GeoLibs Dator - A data extractor
Home-page: https://github.com/GeographicaGS/GeoLibs-Dator
License: MIT
Author: Geographica
Author-email: hello@geographica.com
Requires-Python: >=3.6,<4.0
Classifier: License :: OSI Approved :: MIT License
Classifier: Programming Language :: Python :: 3
Classifier: Programming Language :: Python :: 3.6
Classifier: Programming Language :: Python :: 3.7
Requires-Dist: PyYAML (>=5.1,<6.0)
Requires-Dist: carto (>=1.4,<2.0)
Requires-Dist: cartoframes (>=0.9.2,<0.10.0)
Requires-Dist: google-cloud-bigquery (>=1.11,<2.0)
Requires-Dist: marshmallow (>=2.19,<3.0)
Requires-Dist: numpy (>=1.17,<2.0)
Requires-Dist: pandas (>=0.24.2,<0.25.0)
Requires-Dist: psycopg2-binary (>=2.8.2,<3.0.0)
Requires-Dist: sqlalchemy (>=1.1.15,<2.0.0)
